xpander_utils/__init__.py
xpander_utils/generic.py
xpander_utils/events/__init__.py
xpander_utils/events/git_init.py
xpander_utils/events/listener.py
xpander_utils/events/models/__init__.py
xpander_utils/events/models/deployments.py
xpander_utils/events/models/events.py
xpander_utils/events/models/executions.py
xpander_utils/events/models/memory.py
xpander_utils/sdk/__init__.py
xpander_utils/sdk/adapters/__init__.py
xpander_utils/sdk/adapters/agno.py
xpander_utils/sdk/adapters/base.py
xpander_utils/sdk/adapters/chainlit.py
xpander_utils/sdk/adapters/llamaindex.py
xpander_utils/sdk/adapters/smolagents.py
xpander_utils-0.0.126.dist-info/METADATA
xpander_utils-0.0.126.dist-info/WHEEL
xpander_utils-0.0.126.dist-info/top_level.txt
xpander_utils-0.0.126.dist-info/RECORD
