Metadata-Version: 2.4
Name: xpander_utils
Version: 0.0.126
Summary: A Python utils SDK for xpander.ai services.
Home-page: https://www.xpander.ai
Author: xpanderAI
Author-email: dev@xpander.ai
Classifier: Programming Language :: Python :: 3
Classifier: License :: OSI Approved :: MIT License
Classifier: Operating System :: OS Independent
Requires-Python: >=3.12.1
Requires-Dist: pydantic
Requires-Dist: loguru
Requires-Dist: xpander-sdk==1.64.0
Requires-Dist: httpx
Requires-Dist: httpx_sse
Provides-Extra: smolagents
Requires-Dist: smolagents; extra == "smolagents"
Provides-Extra: llama-index
Requires-Dist: llama_index; extra == "llama-index"
Provides-Extra: chainlit
Requires-Dist: chainlit; extra == "chainlit"
Provides-Extra: agno
Requires-Dist: agno; extra == "agno"
Dynamic: author
Dynamic: author-email
Dynamic: classifier
Dynamic: description
Dynamic: description-content-type
Dynamic: home-page
Dynamic: provides-extra
Dynamic: requires-dist
Dynamic: requires-python
Dynamic: summary
